rbslack/__init__.py
rbslack/admin_urls.py
rbslack/extension.py
rbslack/forms.py
rbslack-0.1.dist-info/DESCRIPTION.rst
rbslack-0.1.dist-info/entry_points.txt
rbslack-0.1.dist-info/METADATA
rbslack-0.1.dist-info/metadata.json
rbslack-0.1.dist-info/RECORD
rbslack-0.1.dist-info/top_level.txt
rbslack-0.1.dist-info/WHEEL
