Metadata-Version: 2.0
Name: rbslack
Version: 0.1
Summary: Review Board integration for slack.com
Home-page: https://www.beanbaginc.com
Author: Beanbag, Inc.
Author-email: support@beanbaginc.com
License: UNKNOWN
Platform: UNKNOWN
Classifier: Development Status :: 4 - Beta
Classifier: Environment :: Web Environment
Classifier: Framework :: Review Board
Classifier: Intended Audience :: Developers
Classifier: License :: OSI Approved :: MIT License
Classifier: Natural Language :: English
Classifier: Operating System :: OS Independent
Classifier: Programming Language :: Python
